{".class":"MypyFile","_fullname":"rich.ansi","future_import_flags":[],"is_partial_stub_package":false,"is_stub":false,"names":{".class":"SymbolTable","AnsiDecoder":{".class":"SymbolTableNode","kind":"Gdef","node":{".class":"TypeInfo","_promote":[],"abstract_attributes":[],"alt_promote":null,"bases":["builtins.object"],"dataclass_transform_spec":null,"declared_metaclass":null,"defn":{".class":"ClassDef","fullname":"rich.ansi.AnsiDecoder","name":"AnsiDecoder","type_vars":[]},"deletable_attributes":[],"deprecated":null,"flags":[],"fullname":"rich.ansi.AnsiDecoder","has_param_spec_type":false,"metaclass_type":null,"metadata":{},"module_name":"rich.ansi","mro":["rich.ansi.AnsiDecoder","builtins.object"],"names":{".class":"SymbolTable","__init__":{".class":"SymbolTableNode","kind":"Mdef","node":{".class":"FuncDef","abstract_status":0,"arg_kinds":[0],"arg_names":["self"],"dataclass_transform_spec":null,"deprecated":null,"flags":[],"fullname":"rich.ansi.AnsiDecoder.__init__","name":"__init__","type":{".class":"CallableType","arg_kinds":[0],"arg_names":["self"],"arg_types":["rich.ansi.AnsiDecoder"],"bound_args":[],"def_extras":{"first_arg":"self"},"fallback":"builtins.function","from_concatenate":false,"implicit":false,"imprecise_arg_kinds":false,"is_ellipsis_args":false,"name":"__init__ of AnsiDecoder","ret_type":{".class":"NoneType"},"type_guard":null,"type_is":null,"unpack_kwargs":false,"variables":[]}}},"decode":{".class":"SymbolTableNode","kind":"Mdef","node":{".class":"FuncDef","abstract_status":0,"arg_kinds":[0,0],"arg_names":["self","terminal_text"],"dataclass_transform_spec":null,"deprecated":null,"flags":[],"fullname":"rich.ansi.AnsiDecoder.decode","name":"decode","type":{".class":"CallableType","arg_kinds":[0,0],"arg_names":["self","terminal_text"],"arg_types":["rich.ansi.AnsiDecoder","builtins.str"],"bound_args":[],"def_extras":{"first_arg":"self"},"fallback":"builtins.function","from_concatenate":false,"implicit":false,"imprecise_arg_kinds":false,"is_ellipsis_args":false,"name":"decode of AnsiDecoder","ret_type":{".class":"Instance","args":["rich.text.Text"],"extra_attrs":null,"type_ref":"typing.Iterable"},"type_guard":null,"type_is":null,"unpack_kwargs":false,"variables":[]}}},"decode_line":{".class":"SymbolTableNode","kind":"Mdef","node":{".class":"FuncDef","abstract_status":0,"arg_kinds":[0,0],"arg_names":["self","line"],"dataclass_transform_spec":null,"deprecated":null,"flags":[],"fullname":"rich.ansi.AnsiDecoder.decode_line","name":"decode_line","type":{".class":"CallableType","arg_kinds":[0,0],"arg_names":["self","line"],"arg_types":["rich.ansi.AnsiDecoder","builtins.str"],"bound_args":[],"def_extras":{"first_arg":"self"},"fallback":"builtins.function","from_concatenate":false,"implicit":false,"imprecise_arg_kinds":false,"is_ellipsis_args":false,"name":"decode_line of AnsiDecoder","ret_type":"rich.text.Text","type_guard":null,"type_is":null,"unpack_kwargs":false,"variables":[]}}},"style":{".class":"SymbolTableNode","implicit":true,"kind":"Mdef","node":{".class":"Var","flags":["is_inferred"],"fullname":"rich.ansi.AnsiDecoder.style","name":"style","type":"rich.style.Style"}}},"self_type":{".class":"TypeVarType","default":{".class":"AnyType","missing_import_name":null,"source_any":null,"type_of_any":4},"fullname":"rich.ansi.AnsiDecoder.Self","id":0,"name":"Self","namespace":"","upper_bound":"rich.ansi.AnsiDecoder","values":[],"variance":0},"slots":null,"tuple_type":null,"type_vars":[],"typeddict_type":null}},"Color":{".class":"SymbolTableNode","cross_ref":"rich.color.Color","kind":"Gdef"},"Console":{".class":"SymbolTableNode","cross_ref":"rich.console.Console","kind":"Gdef"},"Iterable":{".class":"SymbolTableNode","cross_ref":"typing.Iterable","kind":"Gdef"},"NamedTuple":{".class":"SymbolTableNode","cross_ref":"typing.NamedTuple","kind":"Gdef"},"Optional":{".class":"SymbolTableNode","cross_ref":"typing.Optional","kind":"Gdef"},"SGR_STYLE_MAP":{".class":"SymbolTableNode","kind":"Gdef","node":{".class":"Var","flags":["is_inferred","has_explicit_value"],"fullname":"rich.ansi.SGR_STYLE_MAP","name":"SGR_STYLE_MAP","type":{".class":"Instance","args":["builtins.int","builtins.str"],"extra_attrs":null,"type_ref":"builtins.dict"}}},"Style":{".class":"SymbolTableNode","cross_ref":"rich.style.Style","kind":"Gdef"},"Text":{".class":"SymbolTableNode","cross_ref":"rich.text.Text","kind":"Gdef"},"_AnsiToken":{".class":"SymbolTableNode","kind":"Gdef","node":{".class":"TypeInfo","_promote":[],"abstract_attributes":[],"alt_promote":null,"bases":[{".class":"Instance","args":[{".class":"UnionType","items":["builtins.str",{".class":"NoneType"}],"uses_pep604_syntax":false}],"extra_attrs":null,"type_ref":"builtins.tuple"}],"dataclass_transform_spec":null,"declared_metaclass":null,"defn":{".class":"ClassDef","fullname":"rich.ansi._AnsiToken","name":"_AnsiToken","type_vars":[]},"deletable_attributes":[],"deprecated":null,"flags":["is_named_tuple"],"fullname":"rich.ansi._AnsiToken","has_param_spec_type":false,"metaclass_type":null,"metadata":{"namedtuple":{"fields":["plain","sgr","osc"]}},"module_name":"rich.ansi","mro":["rich.ansi._AnsiToken","builtins.tuple","typing.Sequence","typing.Reversible","typing.Collection","typing.Iterable","typing.Container","builtins.object"],"names":{".class":"SymbolTable","_NT":{".class":"SymbolTableNode","kind":"Mdef","node":{".class":"TypeVarExpr","default":{".class":"AnyType","missing_import_name":null,"source_any":null,"type_of_any":4},"fullname":"rich.ansi._AnsiToken._NT","name":"_NT","upper_bound":{".class":"TupleType","implicit":false,"items":["builtins.str",{".class":"UnionType","items":["builtins.str",{".class":"NoneType"}],"uses_pep604_syntax":false},{".class":"UnionType","items":["builtins.str",{".class":"NoneType"}],"uses_pep604_syntax":false}],"partial_fallback":{".class":"Instance","args":[{".class":"UnionType","items":["builtins.str",{".class":"NoneType"}],"uses_pep604_syntax":false}],"extra_attrs":null,"type_ref":"builtins.tuple"}},"values":[],"variance":0}},"__annotations__":{".class":"SymbolTableNode","kind":"Mdef","node":{".class":"Var","flags":["is_initialized_in_class","is_ready"],"fullname":"rich.ansi._AnsiToken.__annotations__","name":"__annotations__","type":{".class":"Instance","args":["builtins.str",{".class":"AnyType","missing_import_name":null,"source_any":null,"type_of_any":6}],"extra_attrs":null,"type_ref":"builtins.dict"}}},"__doc__":{".class":"SymbolTableNode","kind":"Mdef","node":{".class":"Var","flags":["is_initialized_in_class","is_ready"],"fullname":"rich.ansi._AnsiToken.__doc__","name":"__doc__","type":"builtins.str"}},"__match_args__":{".class":"SymbolTableNode","kind":"Mdef","node":{".class":"Var","flags":["is_initialized_in_class","is_ready"],"fullname":"rich.ansi._AnsiToken.__match_args__","name":"__match_args__","type":{".class":"TupleType","implicit":false,"items":[{".class":"LiteralType","fallback":"builtins.str","value":"plain"},{".class":"LiteralType","fallback":"builtins.str","value":"sgr"},{".class":"LiteralType","fallback":"builtins.str","value":"osc"}],"partial_fallback":{".class":"Instance","args":[{".class":"AnyType","missing_import_name":null,"source_any":null,"type_of_any":6}],"extra_attrs":null,"type_ref":"builtins.tuple"}}}},"__new__":{".class":"SymbolTableNode","kind":"Mdef","node":{".class":"FuncDef","abstract_status":0,"arg_kinds":[0,1,1,1],"arg_names":["_cls","plain","sgr","osc"],"dataclass_transform_spec":null,"deprecated":null,"flags":["is_static"],"fullname":"rich.ansi._AnsiToken.__new__","name":"__new__","type":{".class":"CallableType","arg_kinds":[0,1,1,1],"arg_names":["_cls","plain","sgr","osc"],"arg_types":[{".class":"TypeType","item":{".class":"TypeVarType","default":{".class":"AnyType","missing_import_name":null,"source_any":null,"type_of_any":4},"fullname":"rich.ansi._AnsiToken._NT","id":-1,"name":"_NT","namespace":"rich.ansi._AnsiToken.__new__","upper_bound":{".class":"TupleType","implicit":false,"items":["builtins.str",{".class":"UnionType","items":["builtins.str",{".class":"NoneType"}],"uses_pep604_syntax":false},{".class":"UnionType","items":["builtins.str",{".class":"NoneType"}],"uses_pep604_syntax":false}],"partial_fallback":{".class":"Instance","args":[{".class":"UnionType","items":["builtins.str",{".class":"NoneType"}],"uses_pep604_syntax":false}],"extra_attrs":null,"type_ref":"builtins.tuple"}},"values":[],"variance":0}},"builtins.str",{".class":"UnionType","items":["builtins.str",{".class":"NoneType"}],"uses_pep604_syntax":false},{".class":"UnionType","items":["builtins.str",{".class":"NoneType"}],"uses_pep604_syntax":false}],"bound_args":[],"def_extras":{},"fallback":"builtins.function","from_concatenate":false,"implicit":false,"imprecise_arg_kinds":false,"is_ellipsis_args":false,"name":"__new__ of _AnsiToken","ret_type":{".class":"TypeVarType","default":{".class":"AnyType","missing_import_name":null,"source_any":null,"type_of_any":4},"fullname":"rich.ansi._AnsiToken._NT","id":-1,"name":"_NT","namespace":"rich.ansi._AnsiToken.__new__","upper_bound":{".class":"TupleType","implicit":false,"items":["builtins.str",{".class":"UnionType","items":["builtins.str",{".class":"NoneType"}],"uses_pep604_syntax":false},{".class":"UnionType","items":["builtins.str",{".class":"NoneType"}],"uses_pep604_syntax":false}],"partial_fallback":{".class":"Instance","args":[{".class":"UnionType","items":["builtins.str",{".class":"NoneType"}],"uses_pep604_syntax":false}],"extra_attrs":null,"type_ref":"builtins.tuple"}},"values":[],"variance":0},"type_guard":null,"type_is":null,"unpack_kwargs":false,"variables":[{".class":"TypeVarType","default":{".class":"AnyType","missing_import_name":null,"source_any":null,"type_of_any":4},"fullname":"rich.ansi._AnsiToken._NT","id":-1,"name":"_NT","namespace":"rich.ansi._AnsiToken.__new__","upper_bound":{".class":"TupleType","implicit":false,"items":["builtins.str",{".class":"UnionType","items":["builtins.str",{".class":"NoneType"}],"uses_pep604_syntax":false},{".class":"UnionType","items":["builtins.str",{".class":"NoneType"}],"uses_pep604_syntax":false}],"partial_fallback":{".class":"Instance","args":[{".class":"UnionType","items":["builtins.str",{".class":"NoneType"}],"uses_pep604_syntax":false}],"extra_attrs":null,"type_ref":"builtins.tuple"}},"values":[],"variance":0}]}},"plugin_generated":true},"_asdict":{".class":"SymbolTableNode","kind":"Mdef","node":{".class":"FuncDef","abstract_status":0,"arg_kinds":[0],"arg_names":["_self"],"dataclass_transform_spec":null,"deprecated":null,"flags":[],"fullname":"rich.ansi._AnsiToken._asdict","name":"_asdict","type":{".class":"CallableType","arg_kinds":[0],"arg_names":["_self"],"arg_types":[{".class":"TypeVarType","default":{".class":"AnyType","missing_import_name":null,"source_any":null,"type_of_any":4},"fullname":"rich.ansi._AnsiToken._NT","id":-1,"name":"_NT","namespace":"rich.ansi._AnsiToken._asdict","upper_bound":{".class":"TupleType","implicit":false,"items":["builtins.str",{".class":"UnionType","items":["builtins.str",{".class":"NoneType"}],"uses_pep604_syntax":false},{".class":"UnionType","items":["builtins.str",{".class":"NoneType"}],"uses_pep604_syntax":false}],"partial_fallback":{".class":"Instance","args":[{".class":"UnionType","items":["builtins.str",{".class":"NoneType"}],"uses_pep604_syntax":false}],"extra_attrs":null,"type_ref":"builtins.tuple"}},"values":[],"variance":0}],"bound_args":[],"def_extras":{},"fallback":"builtins.function","from_concatenate":false,"implicit":false,"imprecise_arg_kinds":false,"is_ellipsis_args":false,"name":"_asdict of _AnsiToken","ret_type":{".class":"Instance","args":["builtins.str",{".class":"AnyType","missing_import_name":null,"source_any":null,"type_of_any":6}],"extra_attrs":null,"type_ref":"builtins.dict"},"type_guard":null,"type_is":null,"unpack_kwargs":false,"variables":[{".class":"TypeVarType","default":{".class":"AnyType","missing_import_name":null,"source_any":null,"type_of_any":4},"fullname":"rich.ansi._AnsiToken._NT","id":-1,"name":"_NT","namespace":"rich.ansi._AnsiToken._asdict","upper_bound":{".class":"TupleType","implicit":false,"items":["builtins.str",{".class":"UnionType","items":["builtins.str",{".class":"NoneType"}],"uses_pep604_syntax":false},{".class":"UnionType","items":["builtins.str",{".class":"NoneType"}],"uses_pep604_syntax":false}],"partial_fallback":{".class":"Instance","args":[{".class":"UnionType","items":["builtins.str",{".class":"NoneType"}],"uses_pep604_syntax":false}],"extra_attrs":null,"type_ref":"builtins.tuple"}},"values":[],"variance":0}]}},"plugin_generated":true},"_field_defaults":{".class":"SymbolTableNode","kind":"Mdef","node":{".class":"Var","flags":["is_initialized_in_class","is_ready"],"fullname":"rich.ansi._AnsiToken._field_defaults","name":"_field_defaults","type":{".class":"Instance","args":["builtins.str",{".class":"AnyType","missing_import_name":null,"source_any":null,"type_of_any":6}],"extra_attrs":null,"type_ref":"builtins.dict"}}},"_field_types":{".class":"SymbolTableNode","kind":"Mdef","node":{".class":"Var","flags":["is_initialized_in_class","is_ready"],"fullname":"rich.ansi._AnsiToken._field_types","name":"_field_types","type":{".class":"Instance","args":["builtins.str",{".class":"AnyType","missing_import_name":null,"source_any":null,"type_of_any":6}],"extra_attrs":null,"type_ref":"builtins.dict"}}},"_fields":{".class":"SymbolTableNode","kind":"Mdef","node":{".class":"Var","flags":["is_initialized_in_class","is_ready"],"fullname":"rich.ansi._AnsiToken._fields","name":"_fields","type":{".class":"TupleType","implicit":false,"items":["builtins.str","builtins.str","builtins.str"],"partial_fallback":{".class":"Instance","args":[{".class":"AnyType","missing_import_name":null,"source_any":null,"type_of_any":6}],"extra_attrs":null,"type_ref":"builtins.tuple"}}}},"_make":{".class":"SymbolTableNode","kind":"Mdef","node":{".class":"Decorator","func":{".class":"FuncDef","abstract_status":0,"arg_kinds":[0,0],"arg_names":["_cls","iterable"],"dataclass_transform_spec":null,"deprecated":null,"flags":["is_class","is_decorated"],"fullname":"rich.ansi._AnsiToken._make","name":"_make","type":{".class":"CallableType","arg_kinds":[0,0],"arg_names":["_cls","iterable"],"arg_types":[{".class":"TypeType","item":{".class":"TypeVarType","default":{".class":"AnyType","missing_import_name":null,"source_any":null,"type_of_any":4},"fullname":"rich.ansi._AnsiToken._NT","id":-1,"name":"_NT","namespace":"rich.ansi._AnsiToken._make","upper_bound":{".class":"TupleType","implicit":false,"items":["builtins.str",{".class":"UnionType","items":["builtins.str",{".class":"NoneType"}],"uses_pep604_syntax":false},{".class":"UnionType","items":["builtins.str",{".class":"NoneType"}],"uses_pep604_syntax":false}],"partial_fallback":{".class":"Instance","args":[{".class":"UnionType","items":["builtins.str",{".class":"NoneType"}],"uses_pep604_syntax":false}],"extra_attrs":null,"type_ref":"builtins.tuple"}},"values":[],"variance":0}},{".class":"Instance","args":[{".class":"AnyType","missing_import_name":null,"source_any":null,"type_of_any":6}],"extra_attrs":null,"type_ref":"typing.Iterable"}],"bound_args":[],"def_extras":{},"fallback":"builtins.function","from_concatenate":false,"implicit":false,"imprecise_arg_kinds":false,"is_ellipsis_args":false,"name":"_make of _AnsiToken","ret_type":{".class":"TypeVarType","default":{".class":"AnyType","missing_import_name":null,"source_any":null,"type_of_any":4},"fullname":"rich.ansi._AnsiToken._NT","id":-1,"name":"_NT","namespace":"rich.ansi._AnsiToken._make","upper_bound":{".class":"TupleType","implicit":false,"items":["builtins.str",{".class":"UnionType","items":["builtins.str",{".class":"NoneType"}],"uses_pep604_syntax":false},{".class":"UnionType","items":["builtins.str",{".class":"NoneType"}],"uses_pep604_syntax":false}],"partial_fallback":{".class":"Instance","args":[{".class":"UnionType","items":["builtins.str",{".class":"NoneType"}],"uses_pep604_syntax":false}],"extra_attrs":null,"type_ref":"builtins.tuple"}},"values":[],"variance":0},"type_guard":null,"type_is":null,"unpack_kwargs":false,"variables":[{".class":"TypeVarType","default":{".class":"AnyType","missing_import_name":null,"source_any":null,"type_of_any":4},"fullname":"rich.ansi._AnsiToken._NT","id":-1,"name":"_NT","namespace":"rich.ansi._AnsiToken._make","upper_bound":{".class":"TupleType","implicit":false,"items":["builtins.str",{".class":"UnionType","items":["builtins.str",{".class":"NoneType"}],"uses_pep604_syntax":false},{".class":"UnionType","items":["builtins.str",{".class":"NoneType"}],"uses_pep604_syntax":false}],"partial_fallback":{".class":"Instance","args":[{".class":"UnionType","items":["builtins.str",{".class":"NoneType"}],"uses_pep604_syntax":false}],"extra_attrs":null,"type_ref":"builtins.tuple"}},"values":[],"variance":0}]}},"is_overload":false,"var":{".class":"Var","flags":["is_classmethod","is_ready"],"fullname":"rich.ansi._AnsiToken._make","name":"_make","type":{".class":"CallableType","arg_kinds":[0,0],"arg_names":["_cls","iterable"],"arg_types":[{".class":"TypeType","item":{".class":"TypeVarType","default":{".class":"AnyType","missing_import_name":null,"source_any":null,"type_of_any":4},"fullname":"rich.ansi._AnsiToken._NT","id":-1,"name":"_NT","namespace":"rich.ansi._AnsiToken._make","upper_bound":{".class":"TupleType","implicit":false,"items":["builtins.str",{".class":"UnionType","items":["builtins.str",{".class":"NoneType"}],"uses_pep604_syntax":false},{".class":"UnionType","items":["builtins.str",{".class":"NoneType"}],"uses_pep604_syntax":false}],"partial_fallback":{".class":"Instance","args":[{".class":"UnionType","items":["builtins.str",{".class":"NoneType"}],"uses_pep604_syntax":false}],"extra_attrs":null,"type_ref":"builtins.tuple"}},"values":[],"variance":0}},{".class":"Instance","args":[{".class":"AnyType","missing_import_name":null,"source_any":null,"type_of_any":6}],"extra_attrs":null,"type_ref":"typing.Iterable"}],"bound_args":[],"def_extras":{},"fallback":"builtins.function","from_concatenate":false,"implicit":false,"imprecise_arg_kinds":false,"is_ellipsis_args":false,"name":"_make of _AnsiToken","ret_type":{".class":"TypeVarType","default":{".class":"AnyType","missing_import_name":null,"source_any":null,"type_of_any":4},"fullname":"rich.ansi._AnsiToken._NT","id":-1,"name":"_NT","namespace":"rich.ansi._AnsiToken._make","upper_bound":{".class":"TupleType","implicit":false,"items":["builtins.str",{".class":"UnionType","items":["builtins.str",{".class":"NoneType"}],"uses_pep604_syntax":false},{".class":"UnionType","items":["builtins.str",{".class":"NoneType"}],"uses_pep604_syntax":false}],"partial_fallback":{".class":"Instance","args":[{".class":"UnionType","items":["builtins.str",{".class":"NoneType"}],"uses_pep604_syntax":false}],"extra_attrs":null,"type_ref":"builtins.tuple"}},"values":[],"variance":0},"type_guard":null,"type_is":null,"unpack_kwargs":false,"variables":[{".class":"TypeVarType","default":{".class":"AnyType","missing_import_name":null,"source_any":null,"type_of_any":4},"fullname":"rich.ansi._AnsiToken._NT","id":-1,"name":"_NT","namespace":"rich.ansi._AnsiToken._make","upper_bound":{".class":"TupleType","implicit":false,"items":["builtins.str",{".class":"UnionType","items":["builtins.str",{".class":"NoneType"}],"uses_pep604_syntax":false},{".class":"UnionType","items":["builtins.str",{".class":"NoneType"}],"uses_pep604_syntax":false}],"partial_fallback":{".class":"Instance","args":[{".class":"UnionType","items":["builtins.str",{".class":"NoneType"}],"uses_pep604_syntax":false}],"extra_attrs":null,"type_ref":"builtins.tuple"}},"values":[],"variance":0}]}}},"plugin_generated":true},"_replace":{".class":"SymbolTableNode","kind":"Mdef","node":{".class":"FuncDef","abstract_status":0,"arg_kinds":[0,5,5,5],"arg_names":["_self","plain","sgr","osc"],"dataclass_transform_spec":null,"deprecated":null,"flags":[],"fullname":"rich.ansi._AnsiToken._replace","name":"_replace","type":{".class":"CallableType","arg_kinds":[0,5,5,5],"arg_names":["_self","plain","sgr","osc"],"arg_types":[{".class":"TypeVarType","default":{".class":"AnyType","missing_import_name":null,"source_any":null,"type_of_any":4},"fullname":"rich.ansi._AnsiToken._NT","id":-1,"name":"_NT","namespace":"rich.ansi._AnsiToken._replace","upper_bound":{".class":"TupleType","implicit":false,"items":["builtins.str",{".class":"UnionType","items":["builtins.str",{".class":"NoneType"}],"uses_pep604_syntax":false},{".class":"UnionType","items":["builtins.str",{".class":"NoneType"}],"uses_pep604_syntax":false}],"partial_fallback":{".class":"Instance","args":[{".class":"UnionType","items":["builtins.str",{".class":"NoneType"}],"uses_pep604_syntax":false}],"extra_attrs":null,"type_ref":"builtins.tuple"}},"values":[],"variance":0},"builtins.str",{".class":"UnionType","items":["builtins.str",{".class":"NoneType"}],"uses_pep604_syntax":false},{".class":"UnionType","items":["builtins.str",{".class":"NoneType"}],"uses_pep604_syntax":false}],"bound_args":[],"def_extras":{},"fallback":"builtins.function","from_concatenate":false,"implicit":false,"imprecise_arg_kinds":false,"is_ellipsis_args":false,"name":"_replace of _AnsiToken","ret_type":{".class":"TypeVarType","default":{".class":"AnyType","missing_import_name":null,"source_any":null,"type_of_any":4},"fullname":"rich.ansi._AnsiToken._NT","id":-1,"name":"_NT","namespace":"rich.ansi._AnsiToken._replace","upper_bound":{".class":"TupleType","implicit":false,"items":["builtins.str",{".class":"UnionType","items":["builtins.str",{".class":"NoneType"}],"uses_pep604_syntax":false},{".class":"UnionType","items":["builtins.str",{".class":"NoneType"}],"uses_pep604_syntax":false}],"partial_fallback":{".class":"Instance","args":[{".class":"UnionType","items":["builtins.str",{".class":"NoneType"}],"uses_pep604_syntax":false}],"extra_attrs":null,"type_ref":"builtins.tuple"}},"values":[],"variance":0},"type_guard":null,"type_is":null,"unpack_kwargs":false,"variables":[{".class":"TypeVarType","default":{".class":"AnyType","missing_import_name":null,"source_any":null,"type_of_any":4},"fullname":"rich.ansi._AnsiToken._NT","id":-1,"name":"_NT","namespace":"rich.ansi._AnsiToken._replace","upper_bound":{".class":"TupleType","implicit":false,"items":["builtins.str",{".class":"UnionType","items":["builtins.str",{".class":"NoneType"}],"uses_pep604_syntax":false},{".class":"UnionType","items":["builtins.str",{".class":"NoneType"}],"uses_pep604_syntax":false}],"partial_fallback":{".class":"Instance","args":[{".class":"UnionType","items":["builtins.str",{".class":"NoneType"}],"uses_pep604_syntax":false}],"extra_attrs":null,"type_ref":"builtins.tuple"}},"values":[],"variance":0}]}},"plugin_generated":true},"_source":{".class":"SymbolTableNode","kind":"Mdef","node":{".class":"Var","flags":["is_initialized_in_class","is_ready"],"fullname":"rich.ansi._AnsiToken._source","name":"_source","type":"builtins.str"}},"osc":{".class":"SymbolTableNode","kind":"Mdef","node":{".class":"Var","flags":["is_property","is_ready"],"fullname":"rich.ansi._AnsiToken.osc","name":"osc","type":{".class":"UnionType","items":["builtins.str",{".class":"NoneType"}],"uses_pep604_syntax":false}}},"osc-redefinition":{".class":"SymbolTableNode","cross_ref":"rich.ansi._AnsiToken.osc","kind":"Mdef"},"plain":{".class":"SymbolTableNode","kind":"Mdef","node":{".class":"Var","flags":["is_property","is_ready"],"fullname":"rich.ansi._AnsiToken.plain","name":"plain","type":"builtins.str"}},"plain-redefinition":{".class":"SymbolTableNode","cross_ref":"rich.ansi._AnsiToken.plain","kind":"Mdef"},"sgr":{".class":"SymbolTableNode","kind":"Mdef","node":{".class":"Var","flags":["is_property","is_ready"],"fullname":"rich.ansi._AnsiToken.sgr","name":"sgr","type":{".class":"UnionType","items":["builtins.str",{".class":"NoneType"}],"uses_pep604_syntax":false}}},"sgr-redefinition":{".class":"SymbolTableNode","cross_ref":"rich.ansi._AnsiToken.sgr","kind":"Mdef"}},"self_type":{".class":"TypeVarType","default":{".class":"AnyType","missing_import_name":null,"source_any":null,"type_of_any":4},"fullname":"rich.ansi._AnsiToken.Self","id":0,"name":"Self","namespace":"","upper_bound":{".class":"TupleType","implicit":false,"items":["builtins.str",{".class":"UnionType","items":["builtins.str",{".class":"NoneType"}],"uses_pep604_syntax":false},{".class":"UnionType","items":["builtins.str",{".class":"NoneType"}],"uses_pep604_syntax":false}],"partial_fallback":"rich.ansi._AnsiToken"},"values":[],"variance":0},"slots":null,"tuple_type":{".class":"TupleType","implicit":false,"items":["builtins.str",{".class":"UnionType","items":["builtins.str",{".class":"NoneType"}],"uses_pep604_syntax":false},{".class":"UnionType","items":["builtins.str",{".class":"NoneType"}],"uses_pep604_syntax":false}],"partial_fallback":{".class":"Instance","args":[{".class":"UnionType","items":["builtins.str",{".class":"NoneType"}],"uses_pep604_syntax":false}],"extra_attrs":null,"type_ref":"builtins.tuple"}},"type_vars":[],"typeddict_type":null}},"__annotations__":{".class":"SymbolTableNode","kind":"Gdef","node":{".class":"Var","flags":["is_ready"],"fullname":"rich.ansi.__annotations__","name":"__annotations__","type":{".class":"Instance","args":["builtins.str",{".class":"AnyType","missing_import_name":null,"source_any":null,"type_of_any":6}],"extra_attrs":null,"type_ref":"builtins.dict"}}},"__doc__":{".class":"SymbolTableNode","kind":"Gdef","node":{".class":"Var","flags":["is_ready"],"fullname":"rich.ansi.__doc__","name":"__doc__","type":"builtins.str"}},"__file__":{".class":"SymbolTableNode","kind":"Gdef","node":{".class":"Var","flags":["is_ready"],"fullname":"rich.ansi.__file__","name":"__file__","type":"builtins.str"}},"__name__":{".class":"SymbolTableNode","kind":"Gdef","node":{".class":"Var","flags":["is_ready"],"fullname":"rich.ansi.__name__","name":"__name__","type":"builtins.str"}},"__package__":{".class":"SymbolTableNode","kind":"Gdef","node":{".class":"Var","flags":["is_ready"],"fullname":"rich.ansi.__package__","name":"__package__","type":"builtins.str"}},"__spec__":{".class":"SymbolTableNode","kind":"Gdef","node":{".class":"Var","flags":["is_ready"],"fullname":"rich.ansi.__spec__","name":"__spec__","type":"_frozen_importlib.ModuleSpec"}},"_ansi_tokenize":{".class":"SymbolTableNode","kind":"Gdef","node":{".class":"FuncDef","abstract_status":0,"arg_kinds":[0],"arg_names":["ansi_text"],"dataclass_transform_spec":null,"deprecated":null,"flags":[],"fullname":"rich.ansi._ansi_tokenize","name":"_ansi_tokenize","type":{".class":"CallableType","arg_kinds":[0],"arg_names":["ansi_text"],"arg_types":["builtins.str"],"bound_args":[],"def_extras":{"first_arg":null},"fallback":"builtins.function","from_concatenate":false,"implicit":false,"imprecise_arg_kinds":false,"is_ellipsis_args":false,"name":"_ansi_tokenize","ret_type":{".class":"Instance","args":[{".class":"TypeAliasType","args":[],"type_ref":"rich.ansi._AnsiToken"}],"extra_attrs":null,"type_ref":"typing.Iterable"},"type_guard":null,"type_is":null,"unpack_kwargs":false,"variables":[]}}},"console":{".class":"SymbolTableNode","kind":"Gdef","node":{".class":"Var","flags":["is_inferred","has_explicit_value"],"fullname":"rich.ansi.console","name":"console","type":"rich.console.Console"}},"decoder":{".class":"SymbolTableNode","kind":"Gdef","node":{".class":"Var","flags":["is_inferred","has_explicit_value"],"fullname":"rich.ansi.decoder","name":"decoder","type":"rich.ansi.AnsiDecoder"}},"io":{".class":"SymbolTableNode","cross_ref":"io","kind":"Gdef"},"line":{".class":"SymbolTableNode","kind":"Gdef","node":{".class":"Var","flags":["is_index_var","is_inferred"],"fullname":"rich.ansi.line","name":"line","type":"rich.text.Text"}},"os":{".class":"SymbolTableNode","cross_ref":"os","kind":"Gdef"},"pty":{".class":"SymbolTableNode","cross_ref":"pty","kind":"Gdef"},"re":{".class":"SymbolTableNode","cross_ref":"re","kind":"Gdef"},"re_ansi":{".class":"SymbolTableNode","kind":"Gdef","node":{".class":"Var","flags":["is_inferred","has_explicit_value"],"fullname":"rich.ansi.re_ansi","name":"re_ansi","type":{".class":"Instance","args":["builtins.str"],"extra_attrs":null,"type_ref":"re.Pattern"}}},"read":{".class":"SymbolTableNode","kind":"Gdef","node":{".class":"FuncDef","abstract_status":0,"arg_kinds":[0],"arg_names":["fd"],"dataclass_transform_spec":null,"deprecated":null,"flags":[],"fullname":"rich.ansi.read","name":"read","type":{".class":"CallableType","arg_kinds":[0],"arg_names":["fd"],"arg_types":["builtins.int"],"bound_args":[],"def_extras":{"first_arg":null},"fallback":"builtins.function","from_concatenate":false,"implicit":false,"imprecise_arg_kinds":false,"is_ellipsis_args":false,"name":"read","ret_type":"builtins.bytes","type_guard":null,"type_is":null,"unpack_kwargs":false,"variables":[]}}},"stdout":{".class":"SymbolTableNode","kind":"Gdef","node":{".class":"Var","flags":["is_inferred","has_explicit_value"],"fullname":"rich.ansi.stdout","name":"stdout","type":"_io.BytesIO"}},"stdout_result":{".class":"SymbolTableNode","kind":"Gdef","node":{".class":"Var","flags":["is_inferred","has_explicit_value"],"fullname":"rich.ansi.stdout_result","name":"stdout_result","type":"builtins.str"}},"suppress":{".class":"SymbolTableNode","cross_ref":"contextlib.suppress","kind":"Gdef"},"sys":{".class":"SymbolTableNode","cross_ref":"sys","kind":"Gdef"}},"path":"/home/swast/src/github.com/googleapis/python-bigquery-dataframes-2/.nox/mypy/lib/python3.10/site-packages/rich/ansi.py"}
