{".class":"MypyFile","_fullname":"google.cloud.bigquery.format_options","future_import_flags":[],"is_partial_stub_package":false,"is_stub":false,"names":{".class":"SymbolTable","AvroOptions":{".class":"SymbolTableNode","kind":"Gdef","node":{".class":"TypeInfo","_promote":[],"abstract_attributes":[],"alt_promote":null,"bases":["builtins.object"],"dataclass_transform_spec":null,"declared_metaclass":null,"defn":{".class":"ClassDef","fullname":"google.cloud.bigquery.format_options.AvroOptions","name":"AvroOptions","type_vars":[]},"deletable_attributes":[],"deprecated":null,"flags":[],"fullname":"google.cloud.bigquery.format_options.AvroOptions","has_param_spec_type":false,"metaclass_type":null,"metadata":{},"module_name":"google.cloud.bigquery.format_options","mro":["google.cloud.bigquery.format_options.AvroOptions","builtins.object"],"names":{".class":"SymbolTable","_RESOURCE_NAME":{".class":"SymbolTableNode","kind":"Mdef","node":{".class":"Var","flags":["is_initialized_in_class","is_ready","is_inferred","has_explicit_value"],"fullname":"google.cloud.bigquery.format_options.AvroOptions._RESOURCE_NAME","name":"_RESOURCE_NAME","type":"builtins.str"}},"_SOURCE_FORMAT":{".class":"SymbolTableNode","kind":"Mdef","node":{".class":"Var","flags":["is_initialized_in_class","is_ready","is_inferred","has_explicit_value"],"fullname":"google.cloud.bigquery.format_options.AvroOptions._SOURCE_FORMAT","name":"_SOURCE_FORMAT","type":"builtins.str"}},"__init__":{".class":"SymbolTableNode","kind":"Mdef","node":{".class":"FuncDef","abstract_status":0,"arg_kinds":[0],"arg_names":["self"],"dataclass_transform_spec":null,"deprecated":null,"flags":[],"fullname":"google.cloud.bigquery.format_options.AvroOptions.__init__","name":"__init__","type":null}},"_properties":{".class":"SymbolTableNode","implicit":true,"kind":"Mdef","node":{".class":"Var","flags":["is_inferred","invalid_partial_type"],"fullname":"google.cloud.bigquery.format_options.AvroOptions._properties","name":"_properties","type":{".class":"Instance","args":[{".class":"AnyType","missing_import_name":null,"source_any":null,"type_of_any":1},{".class":"AnyType","missing_import_name":null,"source_any":null,"type_of_any":1}],"extra_attrs":null,"type_ref":"builtins.dict"}}},"from_api_repr":{".class":"SymbolTableNode","kind":"Mdef","node":{".class":"Decorator","func":{".class":"FuncDef","abstract_status":0,"arg_kinds":[0,0],"arg_names":["cls","resource"],"dataclass_transform_spec":null,"deprecated":null,"flags":["is_class","is_decorated"],"fullname":"google.cloud.bigquery.format_options.AvroOptions.from_api_repr","name":"from_api_repr","type":{".class":"CallableType","arg_kinds":[0,0],"arg_names":["cls","resource"],"arg_types":[{".class":"TypeType","item":"google.cloud.bigquery.format_options.AvroOptions"},{".class":"Instance","args":["builtins.str","builtins.bool"],"extra_attrs":null,"type_ref":"builtins.dict"}],"bound_args":[],"def_extras":{"first_arg":"cls"},"fallback":"builtins.function","from_concatenate":false,"implicit":false,"imprecise_arg_kinds":false,"is_ellipsis_args":false,"name":"from_api_repr of AvroOptions","ret_type":"google.cloud.bigquery.format_options.AvroOptions","type_guard":null,"type_is":null,"unpack_kwargs":false,"variables":[]}},"is_overload":false,"var":{".class":"Var","flags":["is_initialized_in_class","is_classmethod","is_ready","is_inferred"],"fullname":"google.cloud.bigquery.format_options.AvroOptions.from_api_repr","name":"from_api_repr","type":{".class":"CallableType","arg_kinds":[0,0],"arg_names":["cls","resource"],"arg_types":[{".class":"TypeType","item":"google.cloud.bigquery.format_options.AvroOptions"},{".class":"Instance","args":["builtins.str","builtins.bool"],"extra_attrs":null,"type_ref":"builtins.dict"}],"bound_args":[],"def_extras":{"first_arg":"cls"},"fallback":"builtins.function","from_concatenate":false,"implicit":false,"imprecise_arg_kinds":false,"is_ellipsis_args":false,"name":"from_api_repr of AvroOptions","ret_type":"google.cloud.bigquery.format_options.AvroOptions","type_guard":null,"type_is":null,"unpack_kwargs":false,"variables":[]}}}},"to_api_repr":{".class":"SymbolTableNode","kind":"Mdef","node":{".class":"FuncDef","abstract_status":0,"arg_kinds":[0],"arg_names":["self"],"dataclass_transform_spec":null,"deprecated":null,"flags":[],"fullname":"google.cloud.bigquery.format_options.AvroOptions.to_api_repr","name":"to_api_repr","type":{".class":"CallableType","arg_kinds":[0],"arg_names":["self"],"arg_types":["google.cloud.bigquery.format_options.AvroOptions"],"bound_args":[],"def_extras":{"first_arg":"self"},"fallback":"builtins.function","from_concatenate":false,"implicit":false,"imprecise_arg_kinds":false,"is_ellipsis_args":false,"name":"to_api_repr of AvroOptions","ret_type":{".class":"Instance","args":[{".class":"AnyType","missing_import_name":null,"source_any":null,"type_of_any":4},{".class":"AnyType","missing_import_name":null,"source_any":null,"type_of_any":4}],"extra_attrs":null,"type_ref":"builtins.dict"},"type_guard":null,"type_is":null,"unpack_kwargs":false,"variables":[]}}},"use_avro_logical_types":{".class":"SymbolTableNode","kind":"Mdef","node":{".class":"OverloadedFuncDef","deprecated":null,"flags":["is_property"],"fullname":"google.cloud.bigquery.format_options.AvroOptions.use_avro_logical_types","impl":null,"items":[{".class":"Decorator","func":{".class":"FuncDef","abstract_status":0,"arg_kinds":[0],"arg_names":["self"],"dataclass_transform_spec":null,"deprecated":null,"flags":["is_property","is_overload","is_decorated"],"fullname":"google.cloud.bigquery.format_options.AvroOptions.use_avro_logical_types","name":"use_avro_logical_types","type":{".class":"CallableType","arg_kinds":[0],"arg_names":["self"],"arg_types":["google.cloud.bigquery.format_options.AvroOptions"],"bound_args":[],"def_extras":{"first_arg":"self"},"fallback":"builtins.function","from_concatenate":false,"implicit":false,"imprecise_arg_kinds":false,"is_ellipsis_args":false,"name":"use_avro_logical_types of AvroOptions","ret_type":{".class":"UnionType","items":["builtins.bool",{".class":"NoneType"}],"uses_pep604_syntax":false},"type_guard":null,"type_is":null,"unpack_kwargs":false,"variables":[]}},"is_overload":true,"var":{".class":"Var","flags":["is_initialized_in_class","is_property","is_settable_property","is_ready","is_inferred"],"fullname":"google.cloud.bigquery.format_options.AvroOptions.use_avro_logical_types","name":"use_avro_logical_types","type":{".class":"CallableType","arg_kinds":[0],"arg_names":["self"],"arg_types":["google.cloud.bigquery.format_options.AvroOptions"],"bound_args":[],"def_extras":{"first_arg":"self"},"fallback":"builtins.function","from_concatenate":false,"implicit":false,"imprecise_arg_kinds":false,"is_ellipsis_args":false,"name":"use_avro_logical_types of AvroOptions","ret_type":{".class":"UnionType","items":["builtins.bool",{".class":"NoneType"}],"uses_pep604_syntax":false},"type_guard":null,"type_is":null,"unpack_kwargs":false,"variables":[]}}},{".class":"Decorator","func":{".class":"FuncDef","abstract_status":0,"arg_kinds":[0,0],"arg_names":["self","value"],"dataclass_transform_spec":null,"deprecated":null,"flags":["is_decorated"],"fullname":"google.cloud.bigquery.format_options.AvroOptions.use_avro_logical_types","name":"use_avro_logical_types","type":null},"is_overload":false,"var":{".class":"Var","flags":["is_inferred"],"fullname":"","name":"use_avro_logical_types","type":null}}],"type":{".class":"Overloaded","items":[{".class":"CallableType","arg_kinds":[0],"arg_names":["self"],"arg_types":["google.cloud.bigquery.format_options.AvroOptions"],"bound_args":[],"def_extras":{"first_arg":"self"},"fallback":"builtins.function","from_concatenate":false,"implicit":false,"imprecise_arg_kinds":false,"is_ellipsis_args":false,"name":"use_avro_logical_types of AvroOptions","ret_type":{".class":"UnionType","items":["builtins.bool",{".class":"NoneType"}],"uses_pep604_syntax":false},"type_guard":null,"type_is":null,"unpack_kwargs":false,"variables":[]}]}}}},"self_type":{".class":"TypeVarType","default":{".class":"AnyType","missing_import_name":null,"source_any":null,"type_of_any":4},"fullname":"google.cloud.bigquery.format_options.AvroOptions.Self","id":0,"name":"Self","namespace":"","upper_bound":"google.cloud.bigquery.format_options.AvroOptions","values":[],"variance":0},"slots":null,"tuple_type":null,"type_vars":[],"typeddict_type":null}},"Dict":{".class":"SymbolTableNode","cross_ref":"typing.Dict","kind":"Gdef"},"Optional":{".class":"SymbolTableNode","cross_ref":"typing.Optional","kind":"Gdef"},"ParquetOptions":{".class":"SymbolTableNode","kind":"Gdef","node":{".class":"TypeInfo","_promote":[],"abstract_attributes":[],"alt_promote":null,"bases":["builtins.object"],"dataclass_transform_spec":null,"declared_metaclass":null,"defn":{".class":"ClassDef","fullname":"google.cloud.bigquery.format_options.ParquetOptions","name":"ParquetOptions","type_vars":[]},"deletable_attributes":[],"deprecated":null,"flags":[],"fullname":"google.cloud.bigquery.format_options.ParquetOptions","has_param_spec_type":false,"metaclass_type":null,"metadata":{},"module_name":"google.cloud.bigquery.format_options","mro":["google.cloud.bigquery.format_options.ParquetOptions","builtins.object"],"names":{".class":"SymbolTable","_RESOURCE_NAME":{".class":"SymbolTableNode","kind":"Mdef","node":{".class":"Var","flags":["is_initialized_in_class","is_ready","is_inferred","has_explicit_value"],"fullname":"google.cloud.bigquery.format_options.ParquetOptions._RESOURCE_NAME","name":"_RESOURCE_NAME","type":"builtins.str"}},"_SOURCE_FORMAT":{".class":"SymbolTableNode","kind":"Mdef","node":{".class":"Var","flags":["is_initialized_in_class","is_ready","is_inferred","has_explicit_value"],"fullname":"google.cloud.bigquery.format_options.ParquetOptions._SOURCE_FORMAT","name":"_SOURCE_FORMAT","type":"builtins.str"}},"__init__":{".class":"SymbolTableNode","kind":"Mdef","node":{".class":"FuncDef","abstract_status":0,"arg_kinds":[0],"arg_names":["self"],"dataclass_transform_spec":null,"deprecated":null,"flags":[],"fullname":"google.cloud.bigquery.format_options.ParquetOptions.__init__","name":"__init__","type":null}},"_properties":{".class":"SymbolTableNode","implicit":true,"kind":"Mdef","node":{".class":"Var","flags":["is_inferred","invalid_partial_type"],"fullname":"google.cloud.bigquery.format_options.ParquetOptions._properties","name":"_properties","type":{".class":"Instance","args":[{".class":"AnyType","missing_import_name":null,"source_any":null,"type_of_any":1},{".class":"AnyType","missing_import_name":null,"source_any":null,"type_of_any":1}],"extra_attrs":null,"type_ref":"builtins.dict"}}},"enable_list_inference":{".class":"SymbolTableNode","kind":"Mdef","node":{".class":"OverloadedFuncDef","deprecated":null,"flags":["is_property"],"fullname":"google.cloud.bigquery.format_options.ParquetOptions.enable_list_inference","impl":null,"items":[{".class":"Decorator","func":{".class":"FuncDef","abstract_status":0,"arg_kinds":[0],"arg_names":["self"],"dataclass_transform_spec":null,"deprecated":null,"flags":["is_property","is_overload","is_decorated"],"fullname":"google.cloud.bigquery.format_options.ParquetOptions.enable_list_inference","name":"enable_list_inference","type":{".class":"CallableType","arg_kinds":[0],"arg_names":["self"],"arg_types":["google.cloud.bigquery.format_options.ParquetOptions"],"bound_args":[],"def_extras":{"first_arg":"self"},"fallback":"builtins.function","from_concatenate":false,"implicit":false,"imprecise_arg_kinds":false,"is_ellipsis_args":false,"name":"enable_list_inference of ParquetOptions","ret_type":"builtins.bool","type_guard":null,"type_is":null,"unpack_kwargs":false,"variables":[]}},"is_overload":true,"var":{".class":"Var","flags":["is_initialized_in_class","is_property","is_settable_property","is_ready","is_inferred"],"fullname":"google.cloud.bigquery.format_options.ParquetOptions.enable_list_inference","name":"enable_list_inference","type":{".class":"CallableType","arg_kinds":[0],"arg_names":["self"],"arg_types":["google.cloud.bigquery.format_options.ParquetOptions"],"bound_args":[],"def_extras":{"first_arg":"self"},"fallback":"builtins.function","from_concatenate":false,"implicit":false,"imprecise_arg_kinds":false,"is_ellipsis_args":false,"name":"enable_list_inference of ParquetOptions","ret_type":"builtins.bool","type_guard":null,"type_is":null,"unpack_kwargs":false,"variables":[]}}},{".class":"Decorator","func":{".class":"FuncDef","abstract_status":0,"arg_kinds":[0,0],"arg_names":["self","value"],"dataclass_transform_spec":null,"deprecated":null,"flags":["is_decorated"],"fullname":"google.cloud.bigquery.format_options.ParquetOptions.enable_list_inference","name":"enable_list_inference","type":{".class":"CallableType","arg_kinds":[0,0],"arg_names":["self","value"],"arg_types":["google.cloud.bigquery.format_options.ParquetOptions","builtins.bool"],"bound_args":[],"def_extras":{"first_arg":"self"},"fallback":"builtins.function","from_concatenate":false,"implicit":false,"imprecise_arg_kinds":false,"is_ellipsis_args":false,"name":"enable_list_inference of ParquetOptions","ret_type":{".class":"NoneType"},"type_guard":null,"type_is":null,"unpack_kwargs":false,"variables":[]}},"is_overload":false,"var":{".class":"Var","flags":["is_inferred"],"fullname":"","name":"enable_list_inference","type":null}}],"type":{".class":"Overloaded","items":[{".class":"CallableType","arg_kinds":[0],"arg_names":["self"],"arg_types":["google.cloud.bigquery.format_options.ParquetOptions"],"bound_args":[],"def_extras":{"first_arg":"self"},"fallback":"builtins.function","from_concatenate":false,"implicit":false,"imprecise_arg_kinds":false,"is_ellipsis_args":false,"name":"enable_list_inference of ParquetOptions","ret_type":"builtins.bool","type_guard":null,"type_is":null,"unpack_kwargs":false,"variables":[]}]}}},"enum_as_string":{".class":"SymbolTableNode","kind":"Mdef","node":{".class":"OverloadedFuncDef","deprecated":null,"flags":["is_property"],"fullname":"google.cloud.bigquery.format_options.ParquetOptions.enum_as_string","impl":null,"items":[{".class":"Decorator","func":{".class":"FuncDef","abstract_status":0,"arg_kinds":[0],"arg_names":["self"],"dataclass_transform_spec":null,"deprecated":null,"flags":["is_property","is_overload","is_decorated"],"fullname":"google.cloud.bigquery.format_options.ParquetOptions.enum_as_string","name":"enum_as_string","type":{".class":"CallableType","arg_kinds":[0],"arg_names":["self"],"arg_types":["google.cloud.bigquery.format_options.ParquetOptions"],"bound_args":[],"def_extras":{"first_arg":"self"},"fallback":"builtins.function","from_concatenate":false,"implicit":false,"imprecise_arg_kinds":false,"is_ellipsis_args":false,"name":"enum_as_string of ParquetOptions","ret_type":"builtins.bool","type_guard":null,"type_is":null,"unpack_kwargs":false,"variables":[]}},"is_overload":true,"var":{".class":"Var","flags":["is_initialized_in_class","is_property","is_settable_property","is_ready","is_inferred"],"fullname":"google.cloud.bigquery.format_options.ParquetOptions.enum_as_string","name":"enum_as_string","type":{".class":"CallableType","arg_kinds":[0],"arg_names":["self"],"arg_types":["google.cloud.bigquery.format_options.ParquetOptions"],"bound_args":[],"def_extras":{"first_arg":"self"},"fallback":"builtins.function","from_concatenate":false,"implicit":false,"imprecise_arg_kinds":false,"is_ellipsis_args":false,"name":"enum_as_string of ParquetOptions","ret_type":"builtins.bool","type_guard":null,"type_is":null,"unpack_kwargs":false,"variables":[]}}},{".class":"Decorator","func":{".class":"FuncDef","abstract_status":0,"arg_kinds":[0,0],"arg_names":["self","value"],"dataclass_transform_spec":null,"deprecated":null,"flags":["is_decorated"],"fullname":"google.cloud.bigquery.format_options.ParquetOptions.enum_as_string","name":"enum_as_string","type":{".class":"CallableType","arg_kinds":[0,0],"arg_names":["self","value"],"arg_types":["google.cloud.bigquery.format_options.ParquetOptions","builtins.bool"],"bound_args":[],"def_extras":{"first_arg":"self"},"fallback":"builtins.function","from_concatenate":false,"implicit":false,"imprecise_arg_kinds":false,"is_ellipsis_args":false,"name":"enum_as_string of ParquetOptions","ret_type":{".class":"NoneType"},"type_guard":null,"type_is":null,"unpack_kwargs":false,"variables":[]}},"is_overload":false,"var":{".class":"Var","flags":["is_inferred"],"fullname":"","name":"enum_as_string","type":null}}],"type":{".class":"Overloaded","items":[{".class":"CallableType","arg_kinds":[0],"arg_names":["self"],"arg_types":["google.cloud.bigquery.format_options.ParquetOptions"],"bound_args":[],"def_extras":{"first_arg":"self"},"fallback":"builtins.function","from_concatenate":false,"implicit":false,"imprecise_arg_kinds":false,"is_ellipsis_args":false,"name":"enum_as_string of ParquetOptions","ret_type":"builtins.bool","type_guard":null,"type_is":null,"unpack_kwargs":false,"variables":[]}]}}},"from_api_repr":{".class":"SymbolTableNode","kind":"Mdef","node":{".class":"Decorator","func":{".class":"FuncDef","abstract_status":0,"arg_kinds":[0,0],"arg_names":["cls","resource"],"dataclass_transform_spec":null,"deprecated":null,"flags":["is_class","is_decorated"],"fullname":"google.cloud.bigquery.format_options.ParquetOptions.from_api_repr","name":"from_api_repr","type":{".class":"CallableType","arg_kinds":[0,0],"arg_names":["cls","resource"],"arg_types":[{".class":"TypeType","item":"google.cloud.bigquery.format_options.ParquetOptions"},{".class":"Instance","args":["builtins.str","builtins.bool"],"extra_attrs":null,"type_ref":"builtins.dict"}],"bound_args":[],"def_extras":{"first_arg":"cls"},"fallback":"builtins.function","from_concatenate":false,"implicit":false,"imprecise_arg_kinds":false,"is_ellipsis_args":false,"name":"from_api_repr of ParquetOptions","ret_type":"google.cloud.bigquery.format_options.ParquetOptions","type_guard":null,"type_is":null,"unpack_kwargs":false,"variables":[]}},"is_overload":false,"var":{".class":"Var","flags":["is_initialized_in_class","is_classmethod","is_ready","is_inferred"],"fullname":"google.cloud.bigquery.format_options.ParquetOptions.from_api_repr","name":"from_api_repr","type":{".class":"CallableType","arg_kinds":[0,0],"arg_names":["cls","resource"],"arg_types":[{".class":"TypeType","item":"google.cloud.bigquery.format_options.ParquetOptions"},{".class":"Instance","args":["builtins.str","builtins.bool"],"extra_attrs":null,"type_ref":"builtins.dict"}],"bound_args":[],"def_extras":{"first_arg":"cls"},"fallback":"builtins.function","from_concatenate":false,"implicit":false,"imprecise_arg_kinds":false,"is_ellipsis_args":false,"name":"from_api_repr of ParquetOptions","ret_type":"google.cloud.bigquery.format_options.ParquetOptions","type_guard":null,"type_is":null,"unpack_kwargs":false,"variables":[]}}}},"map_target_type":{".class":"SymbolTableNode","kind":"Mdef","node":{".class":"OverloadedFuncDef","deprecated":null,"flags":["is_property"],"fullname":"google.cloud.bigquery.format_options.ParquetOptions.map_target_type","impl":null,"items":[{".class":"Decorator","func":{".class":"FuncDef","abstract_status":0,"arg_kinds":[0],"arg_names":["self"],"dataclass_transform_spec":null,"deprecated":null,"flags":["is_property","is_overload","is_decorated"],"fullname":"google.cloud.bigquery.format_options.ParquetOptions.map_target_type","name":"map_target_type","type":{".class":"CallableType","arg_kinds":[0],"arg_names":["self"],"arg_types":["google.cloud.bigquery.format_options.ParquetOptions"],"bound_args":[],"def_extras":{"first_arg":"self"},"fallback":"builtins.function","from_concatenate":false,"implicit":false,"imprecise_arg_kinds":false,"is_ellipsis_args":false,"name":"map_target_type of ParquetOptions","ret_type":{".class":"UnionType","items":["builtins.bool","builtins.str",{".class":"NoneType"}],"uses_pep604_syntax":false},"type_guard":null,"type_is":null,"unpack_kwargs":false,"variables":[]}},"is_overload":true,"var":{".class":"Var","flags":["is_initialized_in_class","is_property","is_settable_property","is_ready","is_inferred"],"fullname":"google.cloud.bigquery.format_options.ParquetOptions.map_target_type","name":"map_target_type","type":{".class":"CallableType","arg_kinds":[0],"arg_names":["self"],"arg_types":["google.cloud.bigquery.format_options.ParquetOptions"],"bound_args":[],"def_extras":{"first_arg":"self"},"fallback":"builtins.function","from_concatenate":false,"implicit":false,"imprecise_arg_kinds":false,"is_ellipsis_args":false,"name":"map_target_type of ParquetOptions","ret_type":{".class":"UnionType","items":["builtins.bool","builtins.str",{".class":"NoneType"}],"uses_pep604_syntax":false},"type_guard":null,"type_is":null,"unpack_kwargs":false,"variables":[]}}},{".class":"Decorator","func":{".class":"FuncDef","abstract_status":0,"arg_kinds":[0,0],"arg_names":["self","value"],"dataclass_transform_spec":null,"deprecated":null,"flags":["is_decorated"],"fullname":"google.cloud.bigquery.format_options.ParquetOptions.map_target_type","name":"map_target_type","type":{".class":"CallableType","arg_kinds":[0,0],"arg_names":["self","value"],"arg_types":["google.cloud.bigquery.format_options.ParquetOptions","builtins.str"],"bound_args":[],"def_extras":{"first_arg":"self"},"fallback":"builtins.function","from_concatenate":false,"implicit":false,"imprecise_arg_kinds":false,"is_ellipsis_args":false,"name":"map_target_type of ParquetOptions","ret_type":{".class":"NoneType"},"type_guard":null,"type_is":null,"unpack_kwargs":false,"variables":[]}},"is_overload":false,"var":{".class":"Var","flags":["is_inferred"],"fullname":"","name":"map_target_type","type":null}}],"type":{".class":"Overloaded","items":[{".class":"CallableType","arg_kinds":[0],"arg_names":["self"],"arg_types":["google.cloud.bigquery.format_options.ParquetOptions"],"bound_args":[],"def_extras":{"first_arg":"self"},"fallback":"builtins.function","from_concatenate":false,"implicit":false,"imprecise_arg_kinds":false,"is_ellipsis_args":false,"name":"map_target_type of ParquetOptions","ret_type":{".class":"UnionType","items":["builtins.bool","builtins.str",{".class":"NoneType"}],"uses_pep604_syntax":false},"type_guard":null,"type_is":null,"unpack_kwargs":false,"variables":[]}]}}},"to_api_repr":{".class":"SymbolTableNode","kind":"Mdef","node":{".class":"FuncDef","abstract_status":0,"arg_kinds":[0],"arg_names":["self"],"dataclass_transform_spec":null,"deprecated":null,"flags":[],"fullname":"google.cloud.bigquery.format_options.ParquetOptions.to_api_repr","name":"to_api_repr","type":{".class":"CallableType","arg_kinds":[0],"arg_names":["self"],"arg_types":["google.cloud.bigquery.format_options.ParquetOptions"],"bound_args":[],"def_extras":{"first_arg":"self"},"fallback":"builtins.function","from_concatenate":false,"implicit":false,"imprecise_arg_kinds":false,"is_ellipsis_args":false,"name":"to_api_repr of ParquetOptions","ret_type":{".class":"Instance","args":[{".class":"AnyType","missing_import_name":null,"source_any":null,"type_of_any":4},{".class":"AnyType","missing_import_name":null,"source_any":null,"type_of_any":4}],"extra_attrs":null,"type_ref":"builtins.dict"},"type_guard":null,"type_is":null,"unpack_kwargs":false,"variables":[]}}}},"self_type":{".class":"TypeVarType","default":{".class":"AnyType","missing_import_name":null,"source_any":null,"type_of_any":4},"fullname":"google.cloud.bigquery.format_options.ParquetOptions.Self","id":0,"name":"Self","namespace":"","upper_bound":"google.cloud.bigquery.format_options.ParquetOptions","values":[],"variance":0},"slots":null,"tuple_type":null,"type_vars":[],"typeddict_type":null}},"Union":{".class":"SymbolTableNode","cross_ref":"typing.Union","kind":"Gdef"},"__annotations__":{".class":"SymbolTableNode","kind":"Gdef","node":{".class":"Var","flags":["is_ready"],"fullname":"google.cloud.bigquery.format_options.__annotations__","name":"__annotations__","type":{".class":"Instance","args":["builtins.str",{".class":"AnyType","missing_import_name":null,"source_any":null,"type_of_any":6}],"extra_attrs":null,"type_ref":"builtins.dict"}}},"__doc__":{".class":"SymbolTableNode","kind":"Gdef","node":{".class":"Var","flags":["is_ready"],"fullname":"google.cloud.bigquery.format_options.__doc__","name":"__doc__","type":"builtins.str"}},"__file__":{".class":"SymbolTableNode","kind":"Gdef","node":{".class":"Var","flags":["is_ready"],"fullname":"google.cloud.bigquery.format_options.__file__","name":"__file__","type":"builtins.str"}},"__name__":{".class":"SymbolTableNode","kind":"Gdef","node":{".class":"Var","flags":["is_ready"],"fullname":"google.cloud.bigquery.format_options.__name__","name":"__name__","type":"builtins.str"}},"__package__":{".class":"SymbolTableNode","kind":"Gdef","node":{".class":"Var","flags":["is_ready"],"fullname":"google.cloud.bigquery.format_options.__package__","name":"__package__","type":"builtins.str"}},"__spec__":{".class":"SymbolTableNode","kind":"Gdef","node":{".class":"Var","flags":["is_ready"],"fullname":"google.cloud.bigquery.format_options.__spec__","name":"__spec__","type":"_frozen_importlib.ModuleSpec"}},"copy":{".class":"SymbolTableNode","cross_ref":"copy","kind":"Gdef"}},"path":"/home/swast/src/github.com/googleapis/python-bigquery-dataframes-2/.nox/mypy/lib/python3.10/site-packages/google/cloud/bigquery/format_options.py"}
